preprocessmzML/__init__.py
preprocessmzML/filters.py
preprocessmzML/main.py
preprocessmzML/preprocess.py
preprocessmzML/utils.py
preprocessmzML-0.1.0.dist-info/LICENSE
preprocessmzML-0.1.0.dist-info/METADATA
preprocessmzML-0.1.0.dist-info/WHEEL
preprocessmzML-0.1.0.dist-info/entry_points.txt
preprocessmzML-0.1.0.dist-info/top_level.txt
preprocessmzML-0.1.0.dist-info/RECORD
