Metadata-Version: 2.1
Name: preprocessmzML
Version: 0.1.0
Summary: A package for preprocessing mzML files for ZooMS analysis
Home-page: https://github.com/bharathabnair/preprocessmzML
Author: Bharath Nair
Author-email: bharath@palaeome.org
License: UNKNOWN
Platform: UNKNOWN
Classifier: Programming Language :: Python :: 3
Classifier: License :: OSI Approved :: MIT License
Classifier: Operating System :: OS Independent
Requires-Python: >=3.6
License-File: LICENSE
Requires-Dist: pyopenms
Requires-Dist: numpy <1.24,>=1.20
Requires-Dist: matplotlib
